tfvars2markdown/__init__.py
tfvars2markdown/main.py
tfvars2markdown-0.0.4.dist-info/LICENSE
tfvars2markdown-0.0.4.dist-info/METADATA
tfvars2markdown-0.0.4.dist-info/WHEEL
tfvars2markdown-0.0.4.dist-info/entry_points.txt
tfvars2markdown-0.0.4.dist-info/top_level.txt
tfvars2markdown-0.0.4.dist-info/RECORD
