Metadata-Version: 2.1
Name: tfvars2markdown
Version: 0.0.4
Summary: Converts Terraform 0.12+ variables file into a Markdown table
Home-page: https://github.com/ivica-k/tfvars2markdown
Author: Ivica Kolenkaš
Author-email: ivica.kolenkas@gmail.com
License: UNKNOWN
Platform: UNKNOWN
Classifier: Programming Language :: Python :: 3
Classifier: License :: OSI Approved :: MIT License
Classifier: Operating System :: OS Independent
Requires-Python: >=3.6
Requires-Dist: python-hcl2 (==0.2.0)
Requires-Dist: pytablewriter (==0.46.1)
